{
  "animals": [
    {
      "id": 1,
      "name": "Doodles",
      "breed": "Poodle",
      "locationId": 1,
      "customerId": 1
    },
    {
      "id": 2,
      "name": "Decker",
      "breed": "German Shepherd",
      "locationId": 2,
      "customerId": 1
    },
    {
      "id": 3,
      "name": "Esme",
      "breed": "Pitbull",
      "locationId": 1,
      "customerId": 1
    },
    {
      "name": "Stevie",
      "breed": "Siamese Cat",
      "locationId": 1,
      "customerId": 1,
      "id": 4
    }
  ],
  "customers": [
    {
      "id": 1,
      "name": "Hannah Hall",
      "address": "7002 Chestnut Ct",
      "phoneNumber": "615-222-1234"
    },
    {
      "name": "Bobby Steele",
      "address": "634 Meadow Lane",
      "phoneNumber": "615-548-6548",
      "id": 2
    }
  ],
  "employees": [
    {
      "id": 1,
      "name": "Emma Beaton",
      "location": "Nashville Kennels North"
    },
    {
      "name": "Kenny Smith",
      "location": "Nashville Kennels East",
      "id": 2
    }
  ],
  "locations": [
    {
      "id": 1,
      "name": "Nashville North",
      "address": "8422 Johnson Pike"
    },
    {
      "id": 2,
      "name": "Nashville South",
      "address": "209 Emory Drive"
    },
    {
      "name": "Nashville Kennels East",
      "address": "214 Elliston Place",
      "id": 3
    }
  ]
}